{
  "name": "mitigation_cb-lowaf",
  "data": [
    {
      "seriesName": "DMD_TRA-P-ACTIVE",
      "seriesValues": [
        [
          2018,
          5.502380092749419
        ],
        [
          2019,
          5.62327857230505
        ],
        [
          2020,
          4.06776828146525
        ],
        [
          2021,
          5.130411004506458
        ],
        [
          2022,
          5.313447368611082
        ],
        [
          2023,
          5.4127837649334145
        ],
        [
          2024,
          6.097514422448883
        ],
        [
          2025,
          6.177301023121289
        ],
        [
          2026,
          6.256859031022388
        ],
        [
          2027,
          6.336366048417222
        ],
        [
          2028,
          6.416001641711772
        ],
        [
          2029,
          6.495968178680224
        ],
        [
          2030,
          6.576408876729924
        ],
        [
          2031,
          6.6428325437231805
        ],
        [
          2032,
          6.709764453433124
        ],
        [
          2033,
          6.777074984215724
        ],
        [
          2034,
          6.8445529022764635
        ],
        [
          2035,
          6.912056521666026
        ],
        [
          2036,
          6.979480413699352
        ],
        [
          2037,
          7.04684264222958
        ],
        [
          2038,
          7.1141566252676105
        ],
        [
          2039,
          7.18143581097673
        ],
        [
          2040,
          7.2486712451651
        ],
        [
          2041,
          7.32230616231576
        ],
        [
          2042,
          7.395941079472641
        ],
        [
          2043,
          7.46957599662833
        ],
        [
          2044,
          7.54321091378039
        ],
        [
          2045,
          7.616845830861839
        ],
        [
          2046,
          7.68603211289377
        ],
        [
          2047,
          7.75521839487681
        ],
        [
          2048,
          7.82440467675948
        ],
        [
          2049,
          7.8935909587076
        ],
        [
          2050,
          7.96277724066945
        ],
        [
          2051,
          8.01141484599752
        ]
      ]
    },
    {
      "seriesName": "DMD_TRA-P-BUS",
      "seriesValues": [
        [
          2018,
          1.2005278511166
        ],
        [
          2019,
          1.234741062424899
        ],
        [
          2020,
          0.893187215551517
        ],
        [
          2021,
          1.126518818667263
        ],
        [
          2022,
          1.166709343053344
        ],
        [
          2023,
          1.1885213018550709
        ],
        [
          2024,
          1.338872212890442
        ],
        [
          2025,
          1.35639148848598
        ],
        [
          2026,
          1.373860574306127
        ],
        [
          2027,
          1.3913184638322011
        ],
        [
          2028,
          1.408804585558638
        ],
        [
          2029,
          1.426363375276189
        ],
        [
          2030,
          1.444026282450252
        ],
        [
          2031,
          1.4586113772975744
        ],
        [
          2032,
          1.473308066342371
        ],
        [
          2033,
          1.4880878917195979
        ],
        [
          2034,
          1.5029044715630249
        ],
        [
          2035,
          1.5177266934789417
        ],
        [
          2036,
          1.5325314099747496
        ],
        [
          2037,
          1.5473225864679492
        ],
        [
          2038,
          1.5621031695394294
        ],
        [
          2039,
          1.5768761115624794
        ],
        [
          2040,
          1.591639446425224
        ],
        [
          2041,
          1.607807957911293
        ],
        [
          2042,
          1.6239764667988512
        ],
        [
          2043,
          1.6401449888534625
        ],
        [
          2044,
          1.6563135012367616
        ],
        [
          2045,
          1.6724820135566862
        ],
        [
          2046,
          1.6876737087736742
        ],
        [
          2047,
          1.7028654031873547
        ],
        [
          2048,
          1.718057109459603
        ],
        [
          2049,
          1.7332488061436715
        ],
        [
          2050,
          1.7484405028276984
        ],
        [
          2051,
          1.759120188233263
        ]
      ]
    },
    {
      "seriesName": "DMD_TRA-P-CAR",
      "seriesValues": [
        [
          2018,
          7.486756452706796
        ],
        [
          2019,
          7.641147773090145
        ],
        [
          2020,
          5.517314280185457
        ],
        [
          2021,
          6.958628894757955
        ],
        [
          2022,
          7.206890121763121
        ],
        [
          2023,
          7.341624963929651
        ],
        [
          2024,
          8.270358839322675
        ],
        [
          2025,
          8.378577331443319
        ],
        [
          2026,
          8.486485771483538
        ],
        [
          2027,
          8.594325048675277
        ],
        [
          2028,
          8.702338723453645
        ],
        [
          2029,
          8.810801272702953
        ],
        [
          2030,
          8.919906944464875
        ],
        [
          2031,
          9.010000649747756
        ],
        [
          2032,
          9.103569107257877
        ],
        [
          2033,
          9.19751075980621
        ],
        [
          2034,
          9.307143364719998
        ],
        [
          2035,
          9.398934001556082
        ],
        [
          2036,
          9.490616224954843
        ],
        [
          2037,
          9.582214599305248
        ],
        [
          2038,
          9.673747369645165
        ],
        [
          2039,
          9.765232823397227
        ],
        [
          2040,
          9.856658784078947
        ],
        [
          2041,
          9.956786679752454
        ],
        [
          2042,
          10.056914586816003
        ],
        [
          2043,
          10.15704249152135
        ],
        [
          2044,
          10.257170394239845
        ],
        [
          2045,
          10.357298297682997
        ],
        [
          2046,
          10.451376997198373
        ],
        [
          2047,
          10.545455697243003
        ],
        [
          2048,
          10.63953438862677
        ],
        [
          2049,
          10.733613082594623
        ],
        [
          2050,
          10.827691778609115
        ],
        [
          2051,
          10.89382862011385
        ]
      ]
    },
    {
      "seriesName": "DMD_TRA-P-LPT",
      "seriesValues": [
        [
          2018,
          0.10986437956754
        ],
        [
          2019,
          0.104992841313784
        ],
        [
          2020,
          0.0860903342817429
        ],
        [
          2021,
          0.1085801269002435
        ],
        [
          2022,
          0.11245391264467221
        ],
        [
          2023,
          0.11455627033720431
        ],
        [
          2024,
          0.1290479245541901
        ],
        [
          2025,
          0.1307365298215705
        ],
        [
          2026,
          0.1324202971769236
        ],
        [
          2027,
          0.1341029853656232
        ],
        [
          2028,
          0.1357883947390469
        ],
        [
          2029,
          0.1374808082170011
        ],
        [
          2030,
          0.13918325684498262
        ],
        [
          2031,
          0.1405890487483791
        ],
        [
          2032,
          0.1420055970979105
        ],
        [
          2033,
          0.1434301585906555
        ],
        [
          2034,
          0.1448582626849214
        ],
        [
          2035,
          0.1462869106567399
        ],
        [
          2036,
          0.1477138713403607
        ],
        [
          2037,
          0.14913952695474542
        ],
        [
          2038,
          0.1505641615258974
        ],
        [
          2039,
          0.1519880596125555
        ],
        [
          2040,
          0.1534110317535772
        ],
        [
          2041,
          0.1549694426918199
        ],
        [
          2042,
          0.1565278536369209
        ],
        [
          2043,
          0.15808626458022793
        ],
        [
          2044,
          0.1596446755201057
        ],
        [
          2045,
          0.1612030863906099
        ],
        [
          2046,
          0.1626673463843556
        ],
        [
          2047,
          0.164131606320751
        ],
        [
          2048,
          0.165595866057919
        ],
        [
          2049,
          0.167060125988507
        ],
        [
          2050,
          0.16852438590533
        ],
        [
          2051,
          0.169553753200414
        ]
      ]
    },
    {
      "seriesName": "DMD_TRA-P-MOT",
      "seriesValues": [
        [
          2018,
          0.0182835518082795
        ],
        [
          2019,
          0.0193393176162449
        ],
        [
          2020,
          0.0139896796162442
        ],
        [
          2021,
          0.0176442709888792
        ],
        [
          2022,
          0.0182737611287634
        ],
        [
          2023,
          0.0186153939831033
        ],
        [
          2024,
          0.0209702879324375
        ],
        [
          2025,
          0.0212446861845257
        ],
        [
          2026,
          0.021518298363935498
        ],
        [
          2027,
          0.0217917351558012
        ],
        [
          2028,
          0.0220656141266096
        ],
        [
          2029,
          0.0223406312460461
        ],
        [
          2030,
          0.0226172787462094
        ],
        [
          2031,
          0.022845720491152598
        ],
        [
          2032,
          0.020290494330783
        ],
        [
          2033,
          0.017876917659909
        ]
      ]
    },
    {
      "seriesName": "DMD_TRA-P-TAXI",
      "seriesValues": [
        [
          2018,
          0.2387487645977918
        ],
        [
          2019,
          0.2528987632765205
        ],
        [
          2020,
          0.1829419604087383
        ],
        [
          2021,
          0.23073277125209005
        ],
        [
          2022,
          0.23896456527924897
        ],
        [
          2023,
          0.2434320615242726
        ],
        [
          2024,
          0.274226834545267
        ],
        [
          2025,
          0.27781512042096496
        ],
        [
          2026,
          0.28139312446025405
        ],
        [
          2027,
          0.2849688362073842
        ],
        [
          2028,
          0.28855033071057934
        ],
        [
          2029,
          0.29214670485484395
        ],
        [
          2030,
          0.29576441461198316
        ],
        [
          2031,
          0.29875171540044393
        ],
        [
          2032,
          0.3017618786627823
        ],
        [
          2033,
          0.30478907067014255
        ],
        [
          2034,
          0.3078238001587205
        ],
        [
          2035,
          0.31085967651262914
        ],
        [
          2036,
          0.31389196718641155
        ],
        [
          2037,
          0.31692148473329756
        ],
        [
          2038,
          0.3199488326624109
        ],
        [
          2039,
          0.3229746155916742
        ],
        [
          2040,
          0.3259984241693294
        ],
        [
          2041,
          0.32931004647927686
        ],
        [
          2042,
          0.3326216680956103
        ],
        [
          2043,
          0.33593328908757375
        ],
        [
          2044,
          0.3392449102048619
        ],
        [
          2045,
          0.3425565429378245
        ],
        [
          2046,
          0.3456680933952039
        ],
        [
          2047,
          0.348779643510174
        ],
        [
          2048,
          0.3518911931396311
        ],
        [
          2049,
          0.3550027422728673
        ],
        [
          2050,
          0.3581142889777863
        ],
        [
          2051,
          0.36030168410842195
        ]
      ]
    }
  ]
}