{
  "name": "mitigation_cb-new",
  "data": [
    {
      "seriesName": "DMD_TRA-F-HTRUCK-ICE",
      "seriesValues": [
        [
          2018,
          21.648
        ],
        [
          2019,
          23.8425
        ],
        [
          2020,
          25.93517209520362
        ],
        [
          2021,
          26.84531698085732
        ],
        [
          2022,
          27.71196196118349
        ],
        [
          2023,
          28.43316656833568
        ],
        [
          2024,
          29.875065846058448
        ],
        [
          2025,
          29.714933513212877
        ],
        [
          2026,
          28.755924681085702
        ],
        [
          2027,
          27.872724619215717
        ],
        [
          2028,
          27.50770317678699
        ],
        [
          2029,
          27.73050230921702
        ],
        [
          2030,
          25.95990467867349
        ],
        [
          2031,
          23.74741315061137
        ],
        [
          2032,
          21.06459858853739
        ],
        [
          2033,
          18.064170060548
        ],
        [
          2034,
          14.89953006317565
        ],
        [
          2035,
          11.840041380024429
        ],
        [
          2036,
          9.16431348866704
        ],
        [
          2037,
          7.03822223186191
        ],
        [
          2038,
          5.4900274673888
        ],
        [
          2039,
          4.208796244690097
        ],
        [
          2040,
          3.3257013666867223
        ],
        [
          2041,
          2.638843710488421
        ],
        [
          2042,
          2.099202823546864
        ],
        [
          2043,
          1.620253739827294
        ],
        [
          2044,
          1.094061056353699
        ],
        [
          2045,
          0.8244764949718502
        ],
        [
          2046,
          0.687456859424775
        ],
        [
          2047,
          0.544685209559006
        ],
        [
          2048,
          0.32795453251275
        ]
      ]
    },
    {
      "seriesName": "DMD_TRA-F-HTRUCK-HEV",
      "seriesValues": [
        [
          2024,
          0.227699999331638
        ],
        [
          2025,
          0.569249999388786
        ],
        [
          2026,
          1.08157499957461
        ],
        [
          2027,
          1.85006249976733
        ],
        [
          2028,
          3.00279375006698
        ],
        [
          2029,
          4.73189062492736
        ],
        [
          2030,
          7.32553593525927
        ],
        [
          2031,
          6.99220122282095
        ],
        [
          2032,
          6.53320501120213
        ],
        [
          2033,
          6.04026944764239
        ],
        [
          2034,
          5.55173334932767
        ],
        [
          2035,
          5.04860546896631
        ],
        [
          2036,
          4.53737379240695
        ],
        [
          2037,
          4.0025585116175
        ],
        [
          2038,
          3.45360621600568
        ],
        [
          2039,
          2.92466795750436
        ],
        [
          2040,
          2.44664097199216
        ],
        [
          2041,
          2.04994201761004
        ],
        [
          2042,
          1.7292006938014
        ],
        [
          2043,
          1.50528172614123
        ],
        [
          2044,
          1.33654806015847
        ],
        [
          2045,
          1.27567488926543
        ],
        [
          2046,
          1.18227594080717
        ],
        [
          2047,
          1.03950429102918
        ],
        [
          2048,
          0.822773614078885
        ],
        [
          2049,
          0.494819081706223
        ]
      ]
    },
    {
      "seriesName": "DMD_TRA-F-HTRUCK-BEV",
      "seriesValues": [
        [
          2025,
          0.227700000586647
        ],
        [
          2026,
          0.569250000986279
        ],
        [
          2027,
          1.08157500148681
        ],
        [
          2028,
          1.85006250214193
        ],
        [
          2029,
          3.00279375303557
        ],
        [
          2030,
          4.73189062921772
        ],
        [
          2031,
          7.32553594030685
        ],
        [
          2032,
          11.2160039034488
        ],
        [
          2033,
          17.0517058322799
        ],
        [
          2034,
          23.743010277357
        ],
        [
          2035,
          27.766646522721
        ],
        [
          2036,
          29.4604737662921
        ],
        [
          2037,
          33.4623703095075
        ],
        [
          2038,
          34.8892528981914
        ],
        [
          2039,
          36.3169178396634
        ],
        [
          2040,
          37.7141878285145
        ],
        [
          2041,
          39.0488140086999
        ],
        [
          2042,
          42.0571543671608
        ],
        [
          2043,
          43.0350422887814
        ],
        [
          2044,
          44.0345169554844
        ],
        [
          2045,
          45.0480809658064
        ],
        [
          2046,
          46.0849569694943
        ],
        [
          2047,
          47.145681087945
        ],
        [
          2048,
          48.2308018929046
        ],
        [
          2049,
          49.3408804736967
        ],
        [
          2050,
          50.5099745499204
        ],
        [
          2051,
          51.6717039374853
        ]
      ]
    },
    {
      "seriesName": "DMD_TRA-F-HTRUCK-FCV",
      "seriesValues": [
        [
          2030,
          0.189714160001081
        ],
        [
          2031,
          0.186923733493038
        ],
        [
          2032,
          0.177102406870537
        ],
        [
          2033,
          0.164772524469071
        ],
        [
          2034,
          0.153502840574393
        ],
        [
          2035,
          0.141647445980288
        ],
        [
          2036,
          0.130425279771171
        ],
        [
          2037,
          0.118284548757801
        ],
        [
          2038,
          0.104768313335367
        ],
        [
          2039,
          0.090337071994705
        ],
        [
          2040,
          0.075728300545041
        ],
        [
          2041,
          0.0632419353332536
        ],
        [
          2042,
          0.0515693267735078
        ],
        [
          2043,
          0.0421822096629086
        ],
        [
          2044,
          0.0334837086975198
        ],
        [
          2045,
          0.0334837086975198
        ],
        [
          2046,
          0.0334837086975198
        ],
        [
          2047,
          0.0334837086975198
        ],
        [
          2048,
          0.0334837086975198
        ],
        [
          2049,
          0.0334837086975198
        ],
        [
          2050,
          1.21129017828686e-08
        ],
        [
          2051,
          2.97977520036641e-08
        ]
      ]
    }
  ]
}